teddr/__init__.py
teddr/gridworld.py
teddr/stats.py
teddr/teddr.py
teddr-0.0.1.dist-info/LICENSE
teddr-0.0.1.dist-info/METADATA
teddr-0.0.1.dist-info/WHEEL
teddr-0.0.1.dist-info/top_level.txt
teddr-0.0.1.dist-info/RECORD
