Metadata-Version: 2.1
Name: teddr
Version: 0.0.1
Summary: transportation event distance distribution reconstruction
Home-page: https://github.com/lmiconsulting/teddr
Author: Lucas H. McCabe
Author-email: lmccabe@lmi.org
License: LICENSE.txt
Classifier: Programming Language :: Python :: 3
Classifier: License :: OSI Approved :: MIT License
Classifier: Operating System :: OS Independent
Requires-Python: >=3.10
License-File: LICENSE
Requires-Dist: lifelines ==0.27.8
Requires-Dist: matplotlib ==3.7.1
Requires-Dist: networkx ==3.2
Requires-Dist: numpy ==1.25.0
Requires-Dist: scipy ==1.11.4
Requires-Dist: setuptools ==68.0.0
Requires-Dist: statsmodels ==0.14.0
